Metadata-Version: 2.1
Name: gitcalendar
Version: 1.0.0
Summary: Tool that generates ics-files from a repositories issues, milestones and iterations, which have a due date.
Home-page: https://gitlab.com/dlr-sc/gitcalendar
Author: Benjamin Moritz Bauer
Author-email: benjamin.bauer@dlr.de
Maintainer: Deutsches Zentrum fuer Luft- und Raumfahrt e.V. (DLR)
License: License :: MIT
Keywords: ics,ical,calendar,icalendar,gitlab
Platform: UNKNOWN
Classifier: Development Status :: 5 - Production/Stable
Classifier: Programming Language :: Python :: 3.6
Classifier: Programming Language :: Python :: 3.7
Classifier: Programming Language :: Python :: 3.8
Classifier: Programming Language :: Python :: 3.9
Requires-Python: >=3.6
Provides-Extra: test
Provides-Extra: develop
